hisoka/__init__.py
hisoka/preprocessing.py
hisoka-0.1.0.dist-info/WHEEL
hisoka-0.1.0.dist-info/METADATA
hisoka-0.1.0.dist-info/RECORD
