Metadata-Version: 2.1
Name: hisoka
Version: 0.1.0
Summary: 
Author: Caio Martins
Author-email: caio.outmatched@gmail.com
Requires-Python: >=3.7.2,<4.0.0
Classifier: Programming Language :: Python :: 3
Classifier: Programming Language :: Python :: 3.10
Classifier: Programming Language :: Python :: 3.8
Classifier: Programming Language :: Python :: 3.9
Requires-Dist: catboost (>=1.0,<2.0)
Requires-Dist: pandas (>=1.3,<2.0)
Requires-Dist: scikit-learn (>=0.23,<0.24)
Requires-Dist: shap (>=0.40,<0.41)
Requires-Dist: xgboost (>=1.5,<2.0)
